{"about_itpmp.md":"CYtxmRFw","about_site.md":"BUCVHIJ3","book_communication.md":"Bhx-TkkY","book_cost.md":"BHEnIaIc","book_guide.md":"CM67tH_s","book_integration.md":"CxAN5qf2","book_performance.md":"CnAPzGlt","book_progress.md":"BRvoKN0J","book_purchase.md":"BhCtcJ1C","book_quality.md":"D1z8bEU2","book_related.md":"fjK0xbag","book_resource.md":"EsXiNXdy","book_risk.md":"CHL5qsap","book_scope.md":"DWSvORFA","book_top-ten-management.md":"BgEjM0Fj","index.md":"BqFh349a","summary_all-tt.md":"rQwcXTvj","summary_calc-concept.md":"B7avW6Df","summary_concept.md":"DNFprn2t","summary_learn-data.md":"DlaAzMqg","summary_performance.md":"CSJOw-QX","summary_thesis-record.md":"A2JYnSH3"}
